saphira/__init__.py
saphira/saphira.py
saphira-0.0.2.dist-info/LICENSE
saphira-0.0.2.dist-info/METADATA
saphira-0.0.2.dist-info/WHEEL
saphira-0.0.2.dist-info/top_level.txt
saphira-0.0.2.dist-info/RECORD
