Metadata-Version: 2.1
Name: saphira
Version: 0.0.2
Summary: Access parameters from the Saphira.ai SysEng SSoT
Author-email: Saphira AI <contact@saphira.ai>
License: MIT License
Project-URL: Homepage, https://www.saphira.ai
Keywords: saphira,parameter,hardware
Classifier: License :: OSI Approved :: MIT License
Classifier: Programming Language :: Python
Classifier: Programming Language :: Python :: 3
Requires-Python: >=3.9
License-File: LICENSE
Requires-Dist: requests
Provides-Extra: dev
Requires-Dist: black ; extra == 'dev'
Requires-Dist: bumpver ; extra == 'dev'
Requires-Dist: isort ; extra == 'dev'
Requires-Dist: pip-tools ; extra == 'dev'
Requires-Dist: pytest ; extra == 'dev'
